LICENSE
MANIFEST.in
README.md
requirements.txt
setup.cfg
setup.py
sgmarkets_api_analytics_rotb/__init__.py
sgmarkets_api_analytics_rotb/__meta__.py
sgmarkets_api_analytics_rotb/_calendar.py
sgmarkets_api_analytics_rotb/_obj_from_dict.py
sgmarkets_api_analytics_rotb/_util.py
sgmarkets_api_analytics_rotb/endpoint.py
sgmarkets_api_analytics_rotb/info.py
sgmarkets_api_analytics_rotb/request_rotb_compute_strategy.py
sgmarkets_api_analytics_rotb/request_rotb_compute_strategy_base.py
sgmarkets_api_analytics_rotb/request_rotb_compute_strategy_components.py
sgmarkets_api_analytics_rotb/request_rotb_compute_strategy_prices.py
sgmarkets_api_analytics_rotb/request_rotb_curves.py
sgmarkets_api_analytics_rotb/response_rotb_compute_strategy.py
sgmarkets_api_analytics_rotb/response_rotb_compute_strategy_components.py
sgmarkets_api_analytics_rotb/response_rotb_compute_strategy_prices.py
sgmarkets_api_analytics_rotb/response_rotb_curves.py
sgmarkets_api_analytics_rotb/risk_analysis.py
sgmarkets_api_analytics_rotb/slice_rotb_compute_strategy.py
sgmarkets_api_analytics_rotb/slice_rotb_compute_strategy_components.py
sgmarkets_api_analytics_rotb/slice_rotb_compute_strategy_components_risk_analysis.py
sgmarkets_api_analytics_rotb/slice_rotb_compute_strategy_prices.py
sgmarkets_api_analytics_rotb/slice_rotb_compute_strategy_prices_risk_analysis.py
sgmarkets_api_analytics_rotb/slice_rotb_compute_strategy_risk_analysis.py
sgmarkets_api_analytics_rotb.egg-info/PKG-INFO
sgmarkets_api_analytics_rotb.egg-info/SOURCES.txt
sgmarkets_api_analytics_rotb.egg-info/dependency_links.txt
sgmarkets_api_analytics_rotb.egg-info/not-zip-safe
sgmarkets_api_analytics_rotb.egg-info/requires.txt
sgmarkets_api_analytics_rotb.egg-info/top_level.txt
sgmarkets_api_analytics_rotb/biz/__init__.py
sgmarkets_api_analytics_rotb/markdown/info.md
sgmarkets_api_analytics_rotb/stat/__init__.py
sgmarkets_api_analytics_rotb/stat/linear_regression.py