Metadata-Version: 1.1
Name: sgmarkets-api-analytics-rotb
Version: 0.4.4
Summary: sgmarket api analytics ROTB helper
Home-page: https://gitlab.com/sgmarkets/sgmarkets-api-analytics-rotb
Author: sgmarkets
Author-email: olivier.borderies@gmail.com
License: MIT
Download-URL: https://gitlab.com/sgmarkets/sgmarkets-api-analytics-rotb/repository/archive.tar.gz?ref=0.4.4
Keywords: sgmarkets,api,rotb
Platform: UNKNOWN
Classifier: Development Status :: 4 - Beta
Classifier: License :: OSI Approved :: MIT License
Classifier: Programming Language :: Python :: 3.5
Classifier: Programming Language :: Python :: 3.6
